odoo/addons/web_widget_numeric_step/README.rst
odoo/addons/web_widget_numeric_step/__init__.py
odoo/addons/web_widget_numeric_step/__manifest__.py
odoo/addons/web_widget_numeric_step/demo/res_users_view.xml
odoo/addons/web_widget_numeric_step/i18n/es.po
odoo/addons/web_widget_numeric_step/i18n/fr.po
odoo/addons/web_widget_numeric_step/i18n/it.po
odoo/addons/web_widget_numeric_step/i18n/web_widget_numeric_step.pot
odoo/addons/web_widget_numeric_step/readme/CONTRIBUTORS.rst
odoo/addons/web_widget_numeric_step/readme/DESCRIPTION.rst
odoo/addons/web_widget_numeric_step/readme/USAGE.rst
odoo/addons/web_widget_numeric_step/static/description/add_two_buttons.png
odoo/addons/web_widget_numeric_step/static/description/icon.png
odoo/addons/web_widget_numeric_step/static/description/index.html
"odoo/addons/web_widget_numeric_step/static/description/step0,25andlimits.gif"
odoo/addons/web_widget_numeric_step/static/description/step10_limit15_placeholder117_with_onchange.gif
odoo/addons/web_widget_numeric_step/static/src/css/numeric_step.scss
odoo/addons/web_widget_numeric_step/static/src/js/numeric_step.js
odoo/addons/web_widget_numeric_step/static/src/xml/numeric_step.xml
odoo/addons/web_widget_numeric_step/view/assets.xml
odoo13_addon_web_widget_numeric_step-13.0.1.1.0.dist-info/METADATA
odoo13_addon_web_widget_numeric_step-13.0.1.1.0.dist-info/WHEEL
odoo13_addon_web_widget_numeric_step-13.0.1.1.0.dist-info/top_level.txt
odoo13_addon_web_widget_numeric_step-13.0.1.1.0.dist-info/RECORD
